favicon/__init__.py
favicon/favicon.py
favicon-0.7.0.dist-info/LICENSE.txt
favicon-0.7.0.dist-info/METADATA
favicon-0.7.0.dist-info/RECORD
favicon-0.7.0.dist-info/WHEEL
favicon-0.7.0.dist-info/top_level.txt
